auth_gateway_serverkit/__init__.py
auth_gateway_serverkit/email.py
auth_gateway_serverkit/http_client.py
auth_gateway_serverkit/logger.py
auth_gateway_serverkit/main.py
auth_gateway_serverkit/password.py
auth_gateway_serverkit/request_handler.py
auth_gateway_serverkit/string.py
auth_gateway_serverkit/firebase/__init__.py
auth_gateway_serverkit/firebase/config.py
auth_gateway_serverkit/firebase/initializer.py
auth_gateway_serverkit/firebase/user_api.py
auth_gateway_serverkit/keycloak/__init__.py
auth_gateway_serverkit/keycloak/cleanup_api.py
auth_gateway_serverkit/keycloak/client_api.py
auth_gateway_serverkit/keycloak/config.py
auth_gateway_serverkit/keycloak/initializer.py
auth_gateway_serverkit/keycloak/roles_api.py
auth_gateway_serverkit/keycloak/user_api.py
auth_gateway_serverkit/keycloak/utils.py
auth_gateway_serverkit/middleware/__init__.py
auth_gateway_serverkit/middleware/auth.py
auth_gateway_serverkit/middleware/config.py
auth_gateway_serverkit/middleware/fb_auth.py
auth_gateway_serverkit/middleware/rbac.py
auth_gateway_serverkit/middleware/schemas.py
auth_gateway_serverkit-0.0.79.dist-info/METADATA
auth_gateway_serverkit-0.0.79.dist-info/WHEEL
auth_gateway_serverkit-0.0.79.dist-info/top_level.txt
auth_gateway_serverkit-0.0.79.dist-info/RECORD
