Metadata-Version: 2.4
Name: auth_gateway_serverkit
Version: 0.0.79
Summary: serverkit for auth-gateway-fastapi-keycloak repository
Author: Echo298327
Author-email: Echo298327 <shalomber17@gmail.com>
Project-URL: Homepage, https://github.com/Echo298327/auth-gateway-serverkit
Classifier: Programming Language :: Python :: 3
Classifier: License :: OSI Approved :: MIT License
Classifier: Operating System :: OS Independent
Requires-Python: >=3.10
Requires-Dist: fastapi==0.115.5
Requires-Dist: httpx==0.27.2
Requires-Dist: aiohttp==3.11.2
Requires-Dist: pydantic==2.9.2
Requires-Dist: pydantic_settings==2.6.1
Requires-Dist: pydantic[email]
Requires-Dist: python-keycloak==3.9.1
Requires-Dist: PyJWT==2.6.0
Requires-Dist: python-dotenv==1.0.1
Requires-Dist: firebase_admin==6.5.0
Requires-Dist: python-multipart
Dynamic: author
